torchpick/__init__.py
torchpick-0.0.1.dist-info/METADATA
torchpick-0.0.1.dist-info/WHEEL
torchpick-0.0.1.dist-info/RECORD
