Metadata-Version: 2.4
Name: torchpick
Version: 0.0.1
Summary: This is a meta package to install PyTorch for different accelerator versions
Requires-Python: >=3.9
Provides-Extra: cpu
Requires-Dist: torch==0.0.1+cpu; extra == 'cpu'
Provides-Extra: cpu-cxx11-abi
Requires-Dist: torch==0.0.1+cpu.cxx11.abi; extra == 'cpu-cxx11-abi'
Provides-Extra: cuda
Requires-Dist: torch==0.0.1+cu124; extra == 'cuda'
Provides-Extra: cuda11-8
Requires-Dist: torch==0.0.1+cu118; extra == 'cuda11-8'
Provides-Extra: cuda12-1
Requires-Dist: torch==0.0.1+cu121; extra == 'cuda12-1'
Provides-Extra: cuda12-4
Requires-Dist: torch==0.0.1+cu124; extra == 'cuda12-4'
Provides-Extra: rocm
Requires-Dist: torch==0.0.1+rocm6.2.4; extra == 'rocm'
Provides-Extra: rocm6-1
Requires-Dist: torch==0.0.1+rocm6.1; extra == 'rocm6-1'
Provides-Extra: rocm6-2
Requires-Dist: torch==0.0.1+rocm6.2.4; extra == 'rocm6-2'
Provides-Extra: xpu
Requires-Dist: torch==0.0.1+xpu; extra == 'xpu'
